{"cameraMode":{"drawMode":0,"name":"Shaded","section":"Shading Mode"},"sceneLighting":true,"audioPlay":false,"sceneViewState":{"showFog":true,"showMaterialUpdate":false,"showSkybox":true,"showFlares":true,"showImageEffects":true,"showParticleSystems":true},"in2DMode":false,"pivot":{"x":98.22225189208985,"y":-14.175338745117188,"z":9.74454116821289},"rotation":{"x":-0.29666680097579958,"y":0.10231856256723404,"z":-0.03198719769716263,"w":-0.9489449858665466},"size":48.40393829345703,"orthographic":false}